LICENSE
dindbox/__init__.py
dindbox/__main__.py
dindbox/box.py
dindbox/cli.py
dindbox/errors.py
dindbox/status_screen.py
dindbox-1.0.0.dist-info/LICENSE
dindbox-1.0.0.dist-info/METADATA
dindbox-1.0.0.dist-info/WHEEL
dindbox-1.0.0.dist-info/entry_points.txt
dindbox-1.0.0.dist-info/RECORD
