Metadata-Version: 2.1
Name: dindbox
Version: 1.0.0
Summary: Lightweight, docker-capable virtual testing environment based on docker-in-docker (dind)
Home-page: https://gitlab.com/orbelico/dindbox
License: MIT
Keywords: docker,docker-in-docker,dind,gitlab CI,gitlab runner,github actions
Author: Orbelico
Author-email: orbelico@posteo.de
Requires-Python: >=3.10,<4.0
Classifier: License :: OSI Approved :: MIT License
Classifier: Operating System :: POSIX :: Linux
Classifier: Programming Language :: Python :: 3
Classifier: Programming Language :: Python :: 3.10
Classifier: Programming Language :: Python :: 3.11
Classifier: Programming Language :: Python :: 3.12
Requires-Dist: blessed (>=1.20.0,<2.0.0)
Requires-Dist: configargparse (>=1.7,<2.0)
Requires-Dist: docker (>=6.0.1,<7.0.0)
Requires-Dist: toml (>=0.10.2,<0.11.0)
Project-URL: Repository, https://gitlab.com/orbelico/dindbox
